{"objects": ["Large water bottle - RDM", "glass case", "Glasses", "coffee pod", "Travel mugs - RDM", "tape"], "date": "06_02_2021_15_59_33", "num_objects": 6, "experiment_ID": "Experiment_1_Basket_22", "Large water bottle - RDM": {"roi_bounds": [49, 128, 104, 198], "gaze_x": 224, "gaze_y": -12, "t_start": 1622666034233, "t_select": 1622666038747, "t_close": 1622666047868, "t_completion": 1622666050397, "NOSC": 0, "NGSC": 0, "NAC": 0, "TTA": 9121, "TTG": 13635, "OST": 4514, "TTT": 16164, "success": true, "fail_reason": {"prosthetic_err": true, "obj_select_err": false, "grasp_config_err": false, "aperture_err": false}}, "glass case": {"roi_bounds": [193, 222, 337, 285], "gaze_x": 61, "gaze_y": -1, "t_start": 1622666061373, "t_select": 1622666067947, "t_close": 1622666075588, "t_completion": 1622666078015, "NOSC": 0, "NGSC": 0, "NAC": 0, "TTA": 7641, "TTG": 14215, "OST": 6574, "TTT": 16642, "success": false, "fail_reason": {"prosthetic_err": false, "obj_select_err": true, "grasp_config_err": false, "aperture_err": false}}, "Glasses": {"roi_bounds": [193, 190, 313, 296], "gaze_x": 190, "gaze_y": 76, "t_start": 1622666097173, "t_select": 1622666100830, "t_close": 1622666103046, "t_completion": 1622666105234, "NOSC": 0, "NGSC": 0, "NAC": 0, "TTA": 2216, "TTG": 5873, "OST": 3657, "TTT": 8061, "success": true, "fail_reason": {"prosthetic_err": false, "obj_select_err": false, "grasp_config_err": false, "aperture_err": false}}, "coffee pod": {"roi_bounds": [32, 186, 79, 233], "gaze_x": 48, "gaze_y": -46, "t_start": 1622666111366, "t_select": 1622666114358, "t_close": 1622666117333, "t_completion": 1622666119468, "NOSC": 0, "NGSC": 0, "NAC": 0, "TTA": 2975, "TTG": 5967, "OST": 2992, "TTT": 8102, "success": true, "fail_reason": {"prosthetic_err": false, "obj_select_err": false, "grasp_config_err": false, "aperture_err": false}}, "Travel mugs - RDM": {"roi_bounds": [68, 264, 229, 377], "gaze_x": 54, "gaze_y": -20, "t_start": 1622666124852, "t_select": 1622666126984, "t_close": 1622666131006, "t_completion": 1622666134352, "NOSC": 0, "NGSC": 0, "NAC": 0, "TTA": 4022, "TTG": 6154, "OST": 2132, "TTT": 9500, "success": true, "fail_reason": {"prosthetic_err": false, "obj_select_err": false, "grasp_config_err": false, "aperture_err": false}}, "tape": {"roi_bounds": [58, 161, 106, 221], "gaze_x": 261, "gaze_y": 202, "t_start": 0, "t_select": 0, "t_close": 0, "t_completion": 1622666162436, "NOSC": 0, "NGSC": 0, "NAC": 0, "TTA": 4022, "TTG": 6154, "OST": 0, "TTT": 37584, "success": false, "fail_reason": {"prosthetic_err": false, "obj_select_err": false, "grasp_config_err": false, "aperture_err": false}}}