{"objects": ["white out", "screw driver", "glass case"], "date": "06_01_2021_11_34_59", "num_objects": 3, "experiment_ID": "Experiment_1_Basket_0", "white out": {"roi_bounds": [73, 119, 111, 195], "gaze_x": 428, "gaze_y": -61, "t_start": 1622561747264, "t_select": 1622561773702, "t_close": 1622561779537, "t_completion": 1622561793116, "NOSC": 0, "NGSC": 0, "NAC": 0, "TTA": 5835, "TTG": 32273, "OST": 26438, "TTT": 45852, "success": true, "fail_reason": {"prosthetic_err": false, "obj_select_err": false, "grasp_config_err": false, "aperture_err": false}}, "screw driver": {"roi_bounds": [131, 190, 228, 268], "gaze_x": 24, "gaze_y": -109, "t_start": 1622561814873, "t_select": 1622561823818, "t_close": 1622561832035, "t_completion": 1622561837552, "NOSC": 0, "NGSC": 0, "NAC": 0, "TTA": 8217, "TTG": 17162, "OST": 8945, "TTT": 22679, "success": true, "fail_reason": {"prosthetic_err": false, "obj_select_err": false, "grasp_config_err": false, "aperture_err": false}}, "glass case": {"roi_bounds": [193, 115, 323, 260], "gaze_x": 53, "gaze_y": -158, "t_start": 1622561853952, "t_select": 1622561857648, "t_close": 1622561864170, "t_completion": 1622561868261, "NOSC": 0, "NGSC": 0, "NAC": 0, "TTA": 6522, "TTG": 10218, "OST": 3696, "TTT": 14309, "success": true, "fail_reason": {"prosthetic_err": false, "obj_select_err": false, "grasp_config_err": false, "aperture_err": false}}}